{"cameraMode":{"drawMode":0,"name":"Shaded","section":"Shading Mode"},"sceneLighting":true,"audioPlay":false,"sceneViewState":{"m_AlwaysRefresh":false,"showFog":true,"showSkybox":true,"showFlares":true,"showImageEffects":true,"showParticleSystems":true,"showVisualEffectGraphs":true,"m_FxEnabled":true},"in2DMode":false,"pivot":{"x":-30.903247833251954,"y":-3.2867424488067629,"z":10.751138687133789},"rotation":{"x":0.07854936271905899,"y":-0.5742989778518677,"z":0.05547216162085533,"w":0.8129986524581909},"size":21.1032772064209,"orthographic":false}